README.md
setup.py
func_sorted/__init__.py
func_sorted/mysorted.py
func_sorted.egg-info/PKG-INFO
func_sorted.egg-info/SOURCES.txt
func_sorted.egg-info/dependency_links.txt
func_sorted.egg-info/top_level.txt